Workbook

Sheet Dashboard
B2: Sales Order Management & Customer Analytics — Dashboard
B4: Total Revenue | D4: Total Orders | F4: Total Customers | H4: Avg Order Value
B5: =SUM(Lookup_Orders!E2:E10) -> 34835 | D5: =COUNTA(Lookup_Orders!A2:A10) -> 9 | F5: =COUNTA(Lookup_Customers!A2:A9) -> 8 | H5: =AVERAGE(Lookup_Orders!E2:E10) -> 3870.5556
B8: Charts below are built from the Summary sheets. For the interactive version with Region / Date Range slicers, insert a real PivotTable from the RawDataTable (see note on the RawData sheet).

Sheet Lookup_Categories
A1: CategoryID | B1: CategoryName
A2: 1 | B2: Electronics
A3: 2 | B3: Home Appliances
A4: 3 | B4: Stationery
A5: 4 | B5: Furniture

Sheet Lookup_Products
A1: ProductID | B1: ProductName | C1: CategoryID | D1: CategoryName | E1: UnitPrice | G1: Note: CategoryName is pulled dynamically via VLOOKUP against Lookup_Categories (mirrors Step 3 requirement).
A2: 1 | B2: Wireless Mouse | C2: 1 | D2: =VLOOKUP(C2,Lookup_Categories!$A$2:$B$5,2,FALSE()) -> Electronics | E2: 599
A3: 2 | B3: Bluetooth Keyboard | C3: 1 | D3: =VLOOKUP(C3,Lookup_Categories!$A$2:$B$5,2,FALSE()) -> Electronics | E3: 1299
A4: 3 | B4: LED Desk Lamp | C4: 2 | D4: =VLOOKUP(C4,Lookup_Categories!$A$2:$B$5,2,FALSE()) -> Home Appliances | E4: 899
A5: 4 | B5: Electric Kettle | C5: 2 | D5: =VLOOKUP(C5,Lookup_Categories!$A$2:$B$5,2,FALSE()) -> Home Appliances | E5: 1499
A6: 5 | B6: Notebook Pack (5pcs) | C6: 3 | D6: =VLOOKUP(C6,Lookup_Categories!$A$2:$B$5,2,FALSE()) -> Stationery | E6: 249
A7: 6 | B7: Gel Pen Box (10pcs) | C7: 3 | D7: =VLOOKUP(C7,Lookup_Categories!$A$2:$B$5,2,FALSE()) -> Stationery | E7: 149
A8: 7 | B8: Office Chair | C8: 4 | D8: =VLOOKUP(C8,Lookup_Categories!$A$2:$B$5,2,FALSE()) -> Furniture | E8: 5999
A9: 8 | B9: Study Table | C9: 4 | D9: =VLOOKUP(C9,Lookup_Categories!$A$2:$B$5,2,FALSE()) -> Furniture | E9: 7499

Sheet Lookup_StateRegion
A1: State | B1: Region | D1: Note: all 8 sample customers are based in Maharashtra, so Region will show only 'West' until more geographically varied customers are added.
A2: Maharashtra | B2: West
A3: Gujarat | B3: West
A4: Delhi | B4: North
A5: Punjab | B5: North
A6: Karnataka | B6: South
A7: Tamil Nadu | B7: South
A8: West Bengal | B8: East
A9: Odisha | B9: East

Sheet Lookup_Customers
A1: CustomerID | B1: CustomerName | C1: City | D1: State | E1: Region | F1: CustomerSegment
A2: 1 | B2: Rohan Sharma | C2: Pune | D2: Maharashtra | E2: =VLOOKUP(D2,Lookup_StateRegion!$A$2:$B$9,2,FALSE()) -> West | F2: Retail
A3: 2 | B3: Priya Verma | C3: Pune | D3: Maharashtra | E3: =VLOOKUP(D3,Lookup_StateRegion!$A$2:$B$9,2,FALSE()) -> West | F3: VIP
A4: 3 | B4: Amit Deshmukh | C4: Pune | D4: Maharashtra | E4: =VLOOKUP(D4,Lookup_StateRegion!$A$2:$B$9,2,FALSE()) -> West | F4: Wholesale
A5: 4 | B5: Sneha Kulkarni | C5: Pune | D5: Maharashtra | E5: =VLOOKUP(D5,Lookup_StateRegion!$A$2:$B$9,2,FALSE()) -> West | F5: Retail
A6: 5 | B6: Vikram Joshi | C6: Pune | D6: Maharashtra | E6: =VLOOKUP(D6,Lookup_StateRegion!$A$2:$B$9,2,FALSE()) -> West | F6: Retail
A7: 6 | B7: Neha Patil | C7: Pune | D7: Maharashtra | E7: =VLOOKUP(D7,Lookup_StateRegion!$A$2:$B$9,2,FALSE()) -> West | F7: VIP
A8: 7 | B8: Karan Mehta | C8: Pune | D8: Maharashtra | E8: =VLOOKUP(D8,Lookup_StateRegion!$A$2:$B$9,2,FALSE()) -> West | F8: Wholesale
A9: 8 | B9: Anjali Gupta | C9: Pune | D9: Maharashtra | E9: =VLOOKUP(D9,Lookup_StateRegion!$A$2:$B$9,2,FALSE()) -> West | F9: Retail

Sheet Lookup_Orders
A1: OrderID | B1: OrderDate | C1: CustomerID | D1: Status | E1: TotalAmount | F1: OrderPriority | G1: CancellationReason | I1: Note: OrderPriority is a formula (BR-01: TotalAmount > 1000 = VIP), mirroring the generated column in the MySQL schema.
A2: 1 | B2: 45296 | C2: 1 | D2: Delivered | E2: 1898 | F2: =IF(E2>1000,"VIP","Standard") -> VIP
A3: 2 | B3: 45301 | C3: 2 | D3: Delivered | E3: 6898 | F3: =IF(E3>1000,"VIP","Standard") -> VIP
A4: 3 | B4: 45309 | C4: 3 | D4: Processing | E4: 2998 | F4: =IF(E4>1000,"VIP","Standard") -> VIP
A5: 4 | B5: 45324 | C5: 4 | D5: Delivered | E5: 748 | F5: =IF(E5>1000,"VIP","Standard") -> Standard
A6: 5 | B6: 45336 | C6: 5 | D6: Cancelled | E6: 1499 | F6: =IF(E6>1000,"VIP","Standard") -> VIP | G6: Customer found a better price elsewhere
A7: 6 | B7: 45347 | C7: 1 | D7: Delivered | E7: 899 | F7: =IF(E7>1000,"VIP","Standard") -> Standard
A8: 7 | B8: 45354 | C8: 6 | D8: Pending | E8: 7499 | F8: =IF(E8>1000,"VIP","Standard") -> VIP
A9: 8 | B9: 45366 | C9: 7 | D9: Delivered | E9: 11998 | F9: =IF(E9>1000,"VIP","Standard") -> VIP
A10: 9 | B10: 45372 | C10: 8 | D10: Shipped | E10: 398 | F10: =IF(E10>1000,"VIP","Standard") -> Standard

Sheet RawData
A1: OrderDetailID | B1: OrderID | C1: ProductID | D1: Quantity | E1: UnitPrice | F1: Discount | G1: LineTotal | H1: OrderDate | I1: CustomerID | J1: CustomerName | K1: Region | L1: OrderStatus | M1: OrderPriority | N1: ProductName | O1: CategoryName
A2: 1 | B2: 1 | C2: 1 | D2: 1 | E2: 599 | F2: 0 | G2: =D2*E2*(1-F2/100) -> 599 | H2: =VLOOKUP(B2,Lookup_Orders!$A$2:$G$10,2,FALSE()) -> 45296 | I2: =VLOOKUP(B2,Lookup_Orders!$A$2:$G$10,3,FALSE()) -> 1 | J2: =VLOOKUP(I2,Lookup_Customers!$A$2:$F$9,2,FALSE()) -> Rohan Sharma | K2: =VLOOKUP(I2,Lookup_Customers!$A$2:$F$9,5,FALSE()) -> West | L2: =VLOOKUP(B2,Lookup_Orders!$A$2:$G$10,4,FALSE()) -> Delivered | M2: =VLOOKUP(B2,Lookup_Orders!$A$2:$G$10,6,FALSE()) -> VIP | N2: =VLOOKUP(C2,Lookup_Products!$A$2:$E$9,2,FALSE()) -> Wireless Mouse | O2: =VLOOKUP(C2,Lookup_Products!$A$2:$E$9,4,FALSE()) -> Electronics
A3: 2 | B3: 1 | C3: 5 | D3: 1 | E3: 249 | F3: 0 | G3: =D3*E3*(1-F3/100) -> 249 | H3: =VLOOKUP(B3,Lookup_Orders!$A$2:$G$10,2,FALSE()) -> 45296 | I3: =VLOOKUP(B3,Lookup_Orders!$A$2:$G$10,3,FALSE()) -> 1 | J3: =VLOOKUP(I3,Lookup_Customers!$A$2:$F$9,2,FALSE()) -> Rohan Sharma | K3: =VLOOKUP(I3,Lookup_Customers!$A$2:$F$9,5,FALSE()) -> West | L3: =VLOOKUP(B3,Lookup_Orders!$A$2:$G$10,4,FALSE()) -> Delivered | M3: =VLOOKUP(B3,Lookup_Orders!$A$2:$G$10,6,FALSE()) -> VIP | N3: =VLOOKUP(C3,Lookup_Products!$A$2:$E$9,2,FALSE()) -> Notebook Pack (5pcs) | O3: =VLOOKUP(C3,Lookup_Products!$A$2:$E$9,4,FALSE()) -> Stationery
A4: 3 | B4: 1 | C4: 6 | D4: 1 | E4: 149 | F4: 0 | G4: =D4*E4*(1-F4/100) -> 149 | H4: =VLOOKUP(B4,Lookup_Orders!$A$2:$G$10,2,FALSE()) -> 45296 | I4: =VLOOKUP(B4,Lookup_Orders!$A$2:$G$10,3,FALSE()) -> 1 | J4: =VLOOKUP(I4,Lookup_Customers!$A$2:$F$9,2,FALSE()) -> Rohan Sharma | K4: =VLOOKUP(I4,Lookup_Customers!$A$2:$F$9,5,FALSE()) -> West | L4: =VLOOKUP(B4,Lookup_Orders!$A$2:$G$10,4,FALSE()) -> Delivered | M4: =VLOOKUP(B4,Lookup_Orders!$A$2:$G$10,6,FALSE()) -> VIP | N4: =VLOOKUP(C4,Lookup_Products!$A$2:$E$9,2,FALSE()) -> Gel Pen Box (10pcs) | O4: =VLOOKUP(C4,Lookup_Products!$A$2:$E$9,4,FALSE()) -> Stationery
A5: 4 | B5: 2 | C5: 2 | D5: 1 | E5: 1299 | F5: 0 | G5: =D5*E5*(1-F5/100) -> 1299 | H5: =VLOOKUP(B5,Lookup_Orders!$A$2:$G$10,2,FALSE()) -> 45301 | I5: =VLOOKUP(B5,Lookup_Orders!$A$2:$G$10,3,FALSE()) -> 2 | J5: =VLOOKUP(I5,Lookup_Customers!$A$2:$F$9,2,FALSE()) -> Priya Verma | K5: =VLOOKUP(I5,Lookup_Customers!$A$2:$F$9,5,FALSE()) -> West | L5: =VLOOKUP(B5,Lookup_Orders!$A$2:$G$10,4,FALSE()) -> Delivered | M5: =VLOOKUP(B5,Lookup_Orders!$A$2:$G$10,6,FALSE()) -> VIP | N5: =VLOOKUP(C5,Lookup_Products!$A$2:$E$9,2,FALSE()) -> Bluetooth Keyboard | O5: =VLOOKUP(C5,Lookup_Products!$A$2:$E$9,4,FALSE()) -> Electronics
A6: 5 | B6: 2 | C6: 7 | D6: 1 | E6: 5999 | F6: 0 | G6: =D6*E6*(1-F6/100) -> 5999 | H6: =VLOOKUP(B6,Lookup_Orders!$A$2:$G$10,2,FALSE()) -> 45301 | I6: =VLOOKUP(B6,Lookup_Orders!$A$2:$G$10,3,FALSE()) -> 2 | J6: =VLOOKUP(I6,Lookup_Customers!$A$2:$F$9,2,FALSE()) -> Priya Verma | K6: =VLOOKUP(I6,Lookup_Customers!$A$2:$F$9,5,FALSE()) -> West | L6: =VLOOKUP(B6,Lookup_Orders!$A$2:$G$10,4,FALSE()) -> Delivered | M6: =VLOOKUP(B6,Lookup_Orders!$A$2:$G$10,6,FALSE()) -> VIP | N6: =VLOOKUP(C6,Lookup_Products!$A$2:$E$9,2,FALSE()) -> Office Chair | O6: =VLOOKUP(C6,Lookup_Products!$A$2:$E$9,4,FALSE()) -> Furniture
A7: 6 | B7: 3 | C7: 3 | D7: 1 | E7: 899 | F7: 0 | G7: =D7*E7*(1-F7/100) -> 899 | H7: =VLOOKUP(B7,Lookup_Orders!$A$2:$G$10,2,FALSE()) -> 45309 | I7: =VLOOKUP(B7,Lookup_Orders!$A$2:$G$10,3,FALSE()) -> 3 | J7: =VLOOKUP(I7,Lookup_Customers!$A$2:$F$9,2,FALSE()) -> Amit Deshmukh | K7: =VLOOKUP(I7,Lookup_Customers!$A$2:$F$9,5,FALSE()) -> West | L7: =VLOOKUP(B7,Lookup_Orders!$A$2:$G$10,4,FALSE()) -> Processing | M7: =VLOOKUP(B7,Lookup_Orders!$A$2:$G$10,6,FALSE()) -> VIP | N7: =VLOOKUP(C7,Lookup_Products!$A$2:$E$9,2,FALSE()) -> LED Desk Lamp | O7: =VLOOKUP(C7,Lookup_Products!$A$2:$E$9,4,FALSE()) -> Home Appliances
A8: 7 | B8: 3 | C8: 4 | D8: 1 | E8: 1499 | F8: 0 | G8: =D8*E8*(1-F8/100) -> 1499 | H8: =VLOOKUP(B8,Lookup_Orders!$A$2:$G$10,2,FALSE()) -> 45309 | I8: =VLOOKUP(B8,Lookup_Orders!$A$2:$G$10,3,FALSE()) -> 3 | J8: =VLOOKUP(I8,Lookup_Customers!$A$2:$F$9,2,FALSE()) -> Amit Deshmukh | K8: =VLOOKUP(I8,Lookup_Customers!$A$2:$F$9,5,FALSE()) -> West | L8: =VLOOKUP(B8,Lookup_Orders!$A$2:$G$10,4,FALSE()) -> Processing | M8: =VLOOKUP(B8,Lookup_Orders!$A$2:$G$10,6,FALSE()) -> VIP | N8: =VLOOKUP(C8,Lookup_Products!$A$2:$E$9,2,FALSE()) -> Electric Kettle | O8: =VLOOKUP(C8,Lookup_Products!$A$2:$E$9,4,FALSE()) -> Home Appliances
A9: 8 | B9: 3 | C9: 6 | D9: 4 | E9: 149 | F9: 5 | G9: =D9*E9*(1-F9/100) -> 566.2 | H9: =VLOOKUP(B9,Lookup_Orders!$A$2:$G$10,2,FALSE()) -> 45309 | I9: =VLOOKUP(B9,Lookup_Orders!$A$2:$G$10,3,FALSE()) -> 3 | J9: =VLOOKUP(I9,Lookup_Customers!$A$2:$F$9,2,FALSE()) -> Amit Deshmukh | K9: =VLOOKUP(I9,Lookup_Customers!$A$2:$F$9,5,FALSE()) -> West | L9: =VLOOKUP(B9,Lookup_Orders!$A$2:$G$10,4,FALSE()) -> Processing | M9: =VLOOKUP(B9,Lookup_Orders!$A$2:$G$10,6,FALSE()) -> VIP | N9: =VLOOKUP(C9,Lookup_Products!$A$2:$E$9,2,FALSE()) -> Gel Pen Box (10pcs) | O9: =VLOOKUP(C9,Lookup_Products!$A$2:$E$9,4,FALSE()) -> Stationery
A10: 9 | B10: 4 | C10: 5 | D10: 2 | E10: 249 | F10: 0 | G10: =D10*E10*(1-F10/100) -> 498 | H10: =VLOOKUP(B10,Lookup_Orders!$A$2:$G$10,2,FALSE()) -> 45324 | I10: =VLOOKUP(B10,Lookup_Orders!$A$2:$G$10,3,FALSE()) -> 4 | J10: =VLOOKUP(I10,Lookup_Customers!$A$2:$F$9,2,FALSE()) -> Sneha Kulkarni | K10: =VLOOKUP(I10,Lookup_Customers!$A$2:$F$9,5,FALSE()) -> West | L10: =VLOOKUP(B10,Lookup_Orders!$A$2:$G$10,4,FALSE()) -> Delivered | M10: =VLOOKUP(B10,Lookup_Orders!$A$2:$G$10,6,FALSE()) -> Standard | N10: =VLOOKUP(C10,Lookup_Products!$A$2:$E$9,2,FALSE()) -> Notebook Pack (5pcs) | O10: =VLOOKUP(C10,Lookup_Products!$A$2:$E$9,4,FALSE()) -> Stationery
A11: 10 | B11: 4 | C11: 6 | D11: 1 | E11: 149 | F11: 0 | G11: =D11*E11*(1-F11/100) -> 149 | H11: =VLOOKUP(B11,Lookup_Orders!$A$2:$G$10,2,FALSE()) -> 45324 | I11: =VLOOKUP(B11,Lookup_Orders!$A$2:$G$10,3,FALSE()) -> 4 | J11: =VLOOKUP(I11,Lookup_Customers!$A$2:$F$9,2,FALSE()) -> Sneha Kulkarni | K11: =VLOOKUP(I11,Lookup_Customers!$A$2:$F$9,5,FALSE()) -> West | L11: =VLOOKUP(B11,Lookup_Orders!$A$2:$G$10,4,FALSE()) -> Delivered | M11: =VLOOKUP(B11,Lookup_Orders!$A$2:$G$10,6,FALSE()) -> Standard | N11: =VLOOKUP(C11,Lookup_Products!$A$2:$E$9,2,FALSE()) -> Gel Pen Box (10pcs) | O11: =VLOOKUP(C11,Lookup_Products!$A$2:$E$9,4,FALSE()) -> Stationery
A12: 11 | B12: 5 | C12: 4 | D12: 1 | E12: 1499 | F12: 0 | G12: =D12*E12*(1-F12/100) -> 1499 | H12: =VLOOKUP(B12,Lookup_Orders!$A$2:$G$10,2,FALSE()) -> 45336 | I12: =VLOOKUP(B12,Lookup_Orders!$A$2:$G$10,3,FALSE()) -> 5 | J12: =VLOOKUP(I12,Lookup_Customers!$A$2:$F$9,2,FALSE()) -> Vikram Joshi | K12: =VLOOKUP(I12,Lookup_Customers!$A$2:$F$9,5,FALSE()) -> West | L12: =VLOOKUP(B12,Lookup_Orders!$A$2:$G$10,4,FALSE()) -> Cancelled | M12: =VLOOKUP(B12,Lookup_Orders!$A$2:$G$10,6,FALSE()) -> VIP | N12: =VLOOKUP(C12,Lookup_Products!$A$2:$E$9,2,FALSE()) -> Electric Kettle | O12: =VLOOKUP(C12,Lookup_Products!$A$2:$E$9,4,FALSE()) -> Home Appliances
A13: 12 | B13: 6 | C13: 3 | D13: 1 | E13: 899 | F13: 0 | G13: =D13*E13*(1-F13/100) -> 899 | H13: =VLOOKUP(B13,Lookup_Orders!$A$2:$G$10,2,FALSE()) -> 45347 | I13: =VLOOKUP(B13,Lookup_Orders!$A$2:$G$10,3,FALSE()) -> 1 | J13: =VLOOKUP(I13,Lookup_Customers!$A$2:$F$9,2,FALSE()) -> Rohan Sharma | K13: =VLOOKUP(I13,Lookup_Customers!$A$2:$F$9,5,FALSE()) -> West | L13: =VLOOKUP(B13,Lookup_Orders!$A$2:$G$10,4,FALSE()) -> Delivered | M13: =VLOOKUP(B13,Lookup_Orders!$A$2:$G$10,6,FALSE()) -> Standard | N13: =VLOOKUP(C13,Lookup_Products!$A$2:$E$9,2,FALSE()) -> LED Desk Lamp | O13: =VLOOKUP(C13,Lookup_Products!$A$2:$E$9,4,FALSE()) -> Home Appliances
... A17: 16 | B17: 9 | C17: 6 | D17: 1 | E17: 149 | F17: 0 | G17: =D17*E17*(1-F17/100) -> 149 | H17: =VLOOKUP(B17,Lookup_Orders!$A$2:$G$10,2,FALSE()) -> 45372 | I17: =VLOOKUP(B17,Lookup_Orders!$A$2:$G$10,3,FALSE()) -> 8 | J17: =VLOOKUP(I17,Lookup_Customers!$A$2:$F$9,2,FALSE()) -> Anjali Gupta | K17: =VLOOKUP(I17,Lookup_Customers!$A$2:$F$9,5,FALSE()) -> West | L17: =VLOOKUP(B17,Lookup_Orders!$A$2:$G$10,4,FALSE()) -> Shipped | M17: =VLOOKUP(B17,Lookup_Orders!$A$2:$G$10,6,FALSE()) -> Standard | N17: =VLOOKUP(C17,Lookup_Products!$A$2:$E$9,2,FALSE()) -> Gel Pen Box (10pcs) | O17: =VLOOKUP(C17,Lookup_Products!$A$2:$E$9,4,FALSE()) -> Stationery
A19: Note: this sheet is formatted as an Excel Table ('RawDataTable'). In Excel, select any cell in it and go to Insert > PivotTable to build the three interactive Pivot Tables, then Insert > Slicer for Region and Date Range (openpyxl cannot create native PivotTable/Slicer objects, so the Summary sheets and Dashboard below use SUMIFS formulas as a working stand-in).

Sheet Summary_Category
A1: CategoryName | B1: UnitsSold | C1: Revenue
A2: Electronics | B2: =SUMIF(RawData!$O$2:$O$17,A2,RawData!$D$2:$D$17) -> 2 | C2: =SUMIF(RawData!$O$2:$O$17,A2,RawData!$G$2:$G$17) -> 1898
A3: Home Appliances | B3: =SUMIF(RawData!$O$2:$O$17,A3,RawData!$D$2:$D$17) -> 4 | C3: =SUMIF(RawData!$O$2:$O$17,A3,RawData!$G$2:$G$17) -> 4796
A4: Stationery | B4: =SUMIF(RawData!$O$2:$O$17,A4,RawData!$D$2:$D$17) -> 11 | C4: =SUMIF(RawData!$O$2:$O$17,A4,RawData!$G$2:$G$17) -> 2009.2
A5: Furniture | B5: =SUMIF(RawData!$O$2:$O$17,A5,RawData!$D$2:$D$17) -> 4 | C5: =SUMIF(RawData!$O$2:$O$17,A5,RawData!$G$2:$G$17) -> 25496

Sheet Summary_Monthly
A1: Month | B1: StartDate | C1: EndDate | D1: Revenue | E1: OrderCount
A2: Jan-2024 | B2: 45292 | C2: 45322 | D2: =SUMIFS(Lookup_Orders!$E$2:$E$10,Lookup_Orders!$B$2:$B$10,">="&B2,Lookup_Orders!$B$2:$B$10,"<="&C2) -> 11794 | E2: =COUNTIFS(Lookup_Orders!$B$2:$B$10,">="&B2,Lookup_Orders!$B$2:$B$10,"<="&C2) -> 3
A3: Feb-2024 | B3: 45323 | C3: 45351 | D3: =SUMIFS(Lookup_Orders!$E$2:$E$10,Lookup_Orders!$B$2:$B$10,">="&B3,Lookup_Orders!$B$2:$B$10,"<="&C3) -> 3146 | E3: =COUNTIFS(Lookup_Orders!$B$2:$B$10,">="&B3,Lookup_Orders!$B$2:$B$10,"<="&C3) -> 3
A4: Mar-2024 | B4: 45352 | C4: 45382 | D4: =SUMIFS(Lookup_Orders!$E$2:$E$10,Lookup_Orders!$B$2:$B$10,">="&B4,Lookup_Orders!$B$2:$B$10,"<="&C4) -> 19895 | E4: =COUNTIFS(Lookup_Orders!$B$2:$B$10,">="&B4,Lookup_Orders!$B$2:$B$10,"<="&C4) -> 3

Sheet Summary_OrderStatus
A1: OrderStatus | B1: OrderCount | C1: Revenue
A2: Pending | B2: =COUNTIF(Lookup_Orders!$D$2:$D$10,A2) -> 1 | C2: =SUMIF(Lookup_Orders!$D$2:$D$10,A2,Lookup_Orders!$E$2:$E$10) -> 7499
A3: Processing | B3: =COUNTIF(Lookup_Orders!$D$2:$D$10,A3) -> 1 | C3: =SUMIF(Lookup_Orders!$D$2:$D$10,A3,Lookup_Orders!$E$2:$E$10) -> 2998
A4: Shipped | B4: =COUNTIF(Lookup_Orders!$D$2:$D$10,A4) -> 1 | C4: =SUMIF(Lookup_Orders!$D$2:$D$10,A4,Lookup_Orders!$E$2:$E$10) -> 398
A5: Delivered | B5: =COUNTIF(Lookup_Orders!$D$2:$D$10,A5) -> 5 | C5: =SUMIF(Lookup_Orders!$D$2:$D$10,A5,Lookup_Orders!$E$2:$E$10) -> 22441
A6: Cancelled | B6: =COUNTIF(Lookup_Orders!$D$2:$D$10,A6) -> 1 | C6: =SUMIF(Lookup_Orders!$D$2:$D$10,A6,Lookup_Orders!$E$2:$E$10) -> 1499
